dc_jwtauthenticator/__init__.py
dc_jwtauthenticator/main.py
dc_jhub_jwtauthenticator-0.4.1.dev0.dist-info/METADATA
dc_jhub_jwtauthenticator-0.4.1.dev0.dist-info/WHEEL
dc_jhub_jwtauthenticator-0.4.1.dev0.dist-info/top_level.txt
dc_jhub_jwtauthenticator-0.4.1.dev0.dist-info/RECORD
