Metadata-Version: 2.1
Name: dc-jhub-jwtauthenticator
Version: 0.4.1.dev0
Summary: JSONWebToken Authenticator for JupyterHub
Home-page: UNKNOWN
Author: UNKNOWN
Author-email: UNKNOWN
License: UNKNOWN
Platform: UNKNOWN
Requires-Dist: jupyterhub
Requires-Dist: python-jose
